[
  {
    "text": "Greece",
    "href": "/d/greece/all-events/"
  },
  {
    "text": "Cyprus",
    "href": "/d/cyprus/all-events/"
  },
  {
    "text": "Austria",
    "href": "/d/austria/all-events/"
  },
  {
    "text": "Azerbaijan",
    "href": "/d/azerbaijan/all-events/"
  },
  {
    "text": "Belarus",
    "href": "/d/belarus/all-events/"
  },
  {
    "text": "Belgium",
    "href": "/d/belgium/all-events/"
  },
  {
    "text": "Bulgaria",
    "href": "/d/bulgaria/all-events/"
  },

  {
    "text": "Croatia",
    "href": "/d/croatia/all-events/"
  },
  {
    "text": "Czech Republic",
    "href": "/d/czech-republic/all-events/"
  },
  {
    "text": "Denmark",
    "href": "/d/denmark/all-events/"
  },
  {
    "text": "Estonia",
    "href": "/d/estonia/all-events/"
  },
  {
    "text": "Finland",
    "href": "/d/finland/all-events/"
  },
  {
    "text": "France",
    "href": "/d/france/all-events/"
  },
  {
    "text": "Georgia",
    "href": "/d/georgia/all-events/"
  },
  {
    "text": "Germany",
    "href": "/d/germany/all-events/"
  },

  {
    "text": "Hungary",
    "href": "/d/hungary/all-events/"
  },
  {
    "text": "Iceland",
    "href": "/d/iceland/all-events/"
  },
  {
    "text": "Ireland",
    "href": "/d/ireland/all-events/"
  },
  {
    "text": "Italy",
    "href": "/d/italy/all-events/"
  },
  {
    "text": "Latvia",
    "href": "/d/latvia/all-events/"
  },
  {
    "text": "Lithuania",
    "href": "/d/lithuania/all-events/"
  },
  {
    "text": "Luxembourg",
    "href": "/d/luxembourg/all-events/"
  },
  {
    "text": "Malta",
    "href": "/d/malta/all-events/"
  },
  {
    "text": "Monaco",
    "href": "/d/monaco/all-events/"
  },
  {
    "text": "Montenegro",
    "href": "/d/montenegro/all-events/"
  },
  {
    "text": "Netherlands",
    "href": "/d/netherlands/all-events/"
  },
  {
    "text": "Norway",
    "href": "/d/norway/all-events/"
  },
  {
    "text": "Poland",
    "href": "/d/poland/all-events/"
  },
  {
    "text": "Portugal",
    "href": "/d/portugal/all-events/"
  },
  {
    "text": "Romania",
    "href": "/d/romania/all-events/"
  },
  {
    "text": "Serbia",
    "href": "/d/serbia/all-events/"
  },
  {
    "text": "Slovakia",
    "href": "/d/slovakia/all-events/"
  },
  {
    "text": "Slovenia",
    "href": "/d/slovenia/all-events/"
  },
  {
    "text": "Spain",
    "href": "/d/spain/all-events/"
  },
  {
    "text": "Sweden",
    "href": "/d/sweden/all-events/"
  },
  {
    "text": "Switzerland",
    "href": "/d/switzerland/all-events/"
  },
  {
    "text": "Turkey",
    "href": "/d/turkey/all-events/"
  },
  {
    "text": "Ukraine",
    "href": "/d/ukraine/all-events/"
  },
  {
    "text": "United Kingdom",
    "href": "/d/united-kingdom/all-events/"
  },
  {
    "text": "Bahrain",
    "href": "/d/bahrain/all-events/"
  },
  {
    "text": "Cambodia",
    "href": "/d/cambodia/all-events/"
  },
  {
    "text": "China",
    "href": "/d/china/all-events/"
  },
  {
    "text": "Hong Kong",
    "href": "/d/hong-kong/all-events/"
  },
  {
    "text": "India",
    "href": "/d/india/all-events/"
  },
  {
    "text": "Indonesia",
    "href": "/d/indonesia/all-events/"
  },
  {
    "text": "Israel",
    "href": "/d/israel/all-events/"
  },
  {
    "text": "Japan",
    "href": "/d/japan/all-events/"
  },
  {
    "text": "Lebanon",
    "href": "/d/lebanon/all-events/"
  },
  {
    "text": "Malaysia",
    "href": "/d/malaysia/all-events/"
  },
  {
    "text": "Oman",
    "href": "/d/oman/all-events/"
  },
  {
    "text": "Philippines",
    "href": "/d/philippines/all-events/"
  },
  {
    "text": "Singapore",
    "href": "/d/singapore/all-events/"
  },
  {
    "text": "Thailand",
    "href": "/d/thailand/all-events/"
  },
  {
    "text": "United Arab Emirates",
    "href": "/d/united-arab-emirates/all-events/"
  },
  {
    "text": "Egypt",
    "href": "/d/egypt/all-events/"
  },
  {
    "text": "Morocco",
    "href": "/d/morocco/all-events/"
  }
]